lenskit/sklearn/__init__.py
lenskit/sklearn/svd.py
lenskit_sklearn-2025.1.1b11.dist-info/METADATA
lenskit_sklearn-2025.1.1b11.dist-info/WHEEL
lenskit_sklearn-2025.1.1b11.dist-info/licenses/LICENSE.md
lenskit_sklearn-2025.1.1b11.dist-info/RECORD
