Metadata-Version: 2.4
Name: lenskit-sklearn
Version: 2025.1.1b11
Project-URL: homepage, https://lenskit.org
Project-URL: documentation, https://lkpy.lenskit.org
Project-URL: source, https://github.com/lenskit/lkpy
Author-email: Michael Ekstrand <mdekstrand@drexel.edu>
License: Copyright (c) 2018–2023 Boise State University
License-File: LICENSE.md
Classifier: Intended Audience :: Science/Research
Classifier: License :: OSI Approved :: MIT License
Classifier: Operating System :: OS Independent
Classifier: Programming Language :: Python :: 3
Requires-Python: >=3.11
Requires-Dist: lenskit
Requires-Dist: scikit-learn~=1.2
